{
    "c": [
        {
            "mag": 17.423906874136176,
            "err": 0.014153818957173112,
            "mjd": 58428.607864666665
        },
        {
            "mag": 17.26042119830603,
            "err": 0.016154304880668713,
            "mjd": 58432.6178275
        },
        {
            "mag": 17.297224703034466,
            "err": 0.013099767054811303,
            "mjd": 58436.602534375
        },
        {
            "mag": 17.738428507356772,
            "err": 0.03962623317233742,
            "mjd": 58456.657144
        },
        {
            "mag": 17.867466332084383,
            "err": 0.018430506853323963,
            "mjd": 58460.61269925
        },
        {
            "mag": 18.39257586869017,
            "err": 0.049085100743296715,
            "mjd": 58488.548687
        },
        {
            "mag": 18.422720289240235,
            "err": 0.039837099882071805,
            "mjd": 58492.58125875
        },
        {
            "mag": 19.06375387189108,
            "err": 0.16411744186046515,
            "mjd": 58520.542954
        },
        {
            "mag": 20.298435939919464,
            "err": 9999,
            "mjd": 58576.39986799999
        },
        {
            "mag": 20.823300922211235,
            "err": 0.24940003283388681,
            "mjd": 58580.37854675
        },
        {
            "mag": 20.154343397523345,
            "err": 9999,
            "mjd": 58604.340061999996
        },
        {
            "mag": 20.065105049543938,
            "err": 9999,
            "mjd": 58612.264494749994
        },
        {
            "mag": 20.388317442061688,
            "err": 9999,
            "mjd": 58788.6287892
        },
        {
            "mag": 20.062035555084595,
            "err": 9999,
            "mjd": 58792.61658459999
        },
        {
            "mag": 20.44385251703679,
            "err": 9999,
            "mjd": 58816.5374985
        },
        {
            "mag": 20.426908663491567,
            "err": 9999,
            "mjd": 58868.493439499995
        },
        {
            "mag": 20.501620463868274,
            "err": 9999,
            "mjd": 58872.43371025
        },
        {
            "mag": 20.57793446851567,
            "err": 9999,
            "mjd": 58876.472586125
        },
        {
            "mag": 18.724412928447382,
            "err": 9999,
            "mjd": 58880.43636875
        },
        {
            "mag": 20.878989717944656,
            "err": 9999,
            "mjd": 58900.391448250004
        },
        {
            "mag": 21.02937620258015,
            "err": 9999,
            "mjd": 58932.40130625
        },
        {
            "mag": 21.131167653089257,
            "err": 9999,
            "mjd": 58956.33957899999
        },
        {
            "mag": 21.50906108474457,
            "err": 9999,
            "mjd": 58960.29951333333
        },
        {
            "mag": 14.089301784845295,
            "err": 9999,
            "mjd": 58964.315558
        },
        {
            "mag": 20.80656346549508,
            "err": 9999,
            "mjd": 58980.277551875
        },
        {
            "mag": 20.72643528592906,
            "err": 9999,
            "mjd": 58988.273035
        },
        {
            "mag": 20.135162977051834,
            "err": 9999,
            "mjd": 59140.62968433333
        },
        {
            "mag": 21.365410716752674,
            "err": 9999,
            "mjd": 59144.56917733333
        },
        {
            "mag": 20.039890064332017,
            "err": 9999,
            "mjd": 59176.6517465
        },
        {
            "mag": 21.02941521433701,
            "err": 9999,
            "mjd": 59194.529456000004
        },
        {
            "mag": 20.653144878449247,
            "err": 9999,
            "mjd": 59200.520323000004
        },
        {
            "mag": 21.818887231545318,
            "err": 9999,
            "mjd": 59202.64890075
        },
        {
            "mag": 21.02937620258015,
            "err": 9999,
            "mjd": 59206.49586825
        },
        {
            "mag": 22.03985420122359,
            "err": 9999,
            "mjd": 59222.42465875
        },
        {
            "mag": 20.932283391607136,
            "err": 9999,
            "mjd": 59226.52327575
        },
        {
            "mag": 20.974458704949292,
            "err": 9999,
            "mjd": 59228.5195165
        },
        {
            "mag": 20.947725191557943,
            "err": 9999,
            "mjd": 59230.422447749996
        },
        {
            "mag": 22.007595121715735,
            "err": 9999,
            "mjd": 59250.4242315
        },
        {
            "mag": 20.787777535950188,
            "err": 9999,
            "mjd": 59252.43130575
        },
        {
            "mag": 20.777596295168987,
            "err": 9999,
            "mjd": 59254.4196905
        },
        {
            "mag": 21.52653923348837,
            "err": 9999,
            "mjd": 59256.44801400001
        },
        {
            "mag": 21.564019425768443,
            "err": 9999,
            "mjd": 59258.428132
        },
        {
            "mag": 20.18259972376279,
            "err": 9999,
            "mjd": 59278.36705575
        },
        {
            "mag": 21.91964387238341,
            "err": 9999,
            "mjd": 59284.391235250005
        },
        {
            "mag": 21.556286506502346,
            "err": 9999,
            "mjd": 59288.3484395
        },
        {
            "mag": 22.168374406114513,
            "err": 9999,
            "mjd": 59310.30079550001
        },
        {
            "mag": 20.59207150459671,
            "err": 9999,
            "mjd": 59314.30438733334
        },
        {
            "mag": 20.348452975998725,
            "err": 9999,
            "mjd": 59318.295433
        },
        {
            "mag": 20.344833280029214,
            "err": 9999,
            "mjd": 59344.249631499995
        },
        {
            "mag": 20.640063218393944,
            "err": 9999,
            "mjd": 59524.606392
        },
        {
            "mag": 21.552058657684952,
            "err": 9999,
            "mjd": 59528.539848
        },
        {
            "mag": 21.152568597438734,
            "err": 9999,
            "mjd": 59588.50600933334
        },
        {
            "mag": 20.9442072799072,
            "err": 9999,
            "mjd": 59615.399366749996
        },
        {
            "mag": 20.587018092649792,
            "err": 9999,
            "mjd": 59635.441900499995
        },
        {
            "mag": 20.588131414886053,
            "err": 9999,
            "mjd": 59639.37692925
        },
        {
            "mag": 20.225143324768652,
            "err": 9999,
            "mjd": 59643.404403
        },
        {
            "mag": 20.67677638065195,
            "err": 9999,
            "mjd": 59663.31215975
        },
        {
            "mag": 20.67294030048952,
            "err": 9999,
            "mjd": 59671.331582750005
        },
        {
            "mag": 18.460306268827242,
            "err": 9999,
            "mjd": 59679.2897384
        },
        {
            "mag": 17.90610693004905,
            "err": 9999,
            "mjd": 59691.313763
        },
        {
            "mag": 20.192648126795813,
            "err": 9999,
            "mjd": 59695.2765465
        },
        {
            "mag": 19.128082374483874,
            "err": 9999,
            "mjd": 59699.2917685
        },
        {
            "mag": 18.207877855186602,
            "err": 9999,
            "mjd": 59845.592720750006
        },
        {
            "mag": 20.207196863200842,
            "err": 9999,
            "mjd": 59853.547554
        },
        {
            "mag": 20.38106951503683,
            "err": 9999,
            "mjd": 59883.614167
        },
        {
            "mag": 20.922515625328238,
            "err": 9999,
            "mjd": 59905.586071
        },
        {
            "mag": 20.493124935156164,
            "err": 9999,
            "mjd": 59909.491702
        },
        {
            "mag": 20.02357229107236,
            "err": 9999,
            "mjd": 59927.350816
        },
        {
            "mag": 19.391821371940818,
            "err": 9999,
            "mjd": 60046.30760275
        },
        {
            "mag": 20.64909794930537,
            "err": 9999,
            "mjd": 60048.318631999995
        },
        {
            "mag": 20.602831371033332,
            "err": 9999,
            "mjd": 60050.315594
        },
        {
            "mag": 19.259323984383208,
            "err": 9999,
            "mjd": 60052.29138475
        },
        {
            "mag": 20.268980299407993,
            "err": 9999,
            "mjd": 60056.32465375
        },
        {
            "mag": 20.588891627596126,
            "err": 9999,
            "mjd": 60058.2789315
        }
    ],
    "o": [
        {
            "mag": 17.72177072235265,
            "err": 0.09536554054054054,
            "mjd": 58408.646251
        },
        {
            "mag": 17.4954380489224,
            "err": 0.024873994554214855,
            "mjd": 58412.6391895
        },
        {
            "mag": 17.420251184910395,
            "err": 0.03524247485740622,
            "mjd": 58414.637842833334
        },
        {
            "mag": 17.324139804288272,
            "err": 0.03551480332206924,
            "mjd": 58416.5870985
        },
        {
            "mag": 16.410912013506124,
            "err": 9999,
            "mjd": 58418.654649
        },
        {
            "mag": 17.2424783013773,
            "err": 0.02000078203966576,
            "mjd": 58426.61228166666
        },
        {
            "mag": 17.178469782813625,
            "err": 0.015852409701687904,
            "mjd": 58430.60019375
        },
        {
            "mag": 17.152037413563413,
            "err": 0.019406673239338087,
            "mjd": 58434.590552249996
        },
        {
            "mag": 17.176282733409913,
            "err": 0.09378470782378714,
            "mjd": 58438.592563
        },
        {
            "mag": 17.167867769428536,
            "err": 0.02378874819945004,
            "mjd": 58442.579758750006
        },
        {
            "mag": 17.262461558464963,
            "err": 0.04823944743121544,
            "mjd": 58446.518944999996
        },
        {
            "mag": 17.280957561850908,
            "err": 0.03099543065405174,
            "mjd": 58450.561640750006
        },
        {
            "mag": 17.462030387680848,
            "err": 0.21656250000000005,
            "mjd": 58452.594573
        },
        {
            "mag": 17.267753899057013,
            "err": 0.015970231503300222,
            "mjd": 58454.58751671429
        },
        {
            "mag": 17.284438875207982,
            "err": 0.020786131433221815,
            "mjd": 58458.610988
        },
        {
            "mag": 17.36735663876724,
            "err": 0.019781544342904946,
            "mjd": 58462.57118025
        },
        {
            "mag": 17.396575096688274,
            "err": 0.025119193936765614,
            "mjd": 58466.604044
        },
        {
            "mag": 17.484011441158508,
            "err": 0.023622100963968565,
            "mjd": 58470.581698600006
        },
        {
            "mag": 17.476361632967482,
            "err": 0.03465800787791437,
            "mjd": 58472.563157
        },
        {
            "mag": 17.525394257671497,
            "err": 0.041982308979104654,
            "mjd": 58478.57529675
        },
        {
            "mag": 17.59437861144979,
            "err": 0.01959426443544156,
            "mjd": 58480.56016925
        },
        {
            "mag": 17.621460418079725,
            "err": 0.02436964680402683,
            "mjd": 58486.5278105
        },
        {
            "mag": 17.754043115976366,
            "err": 0.02634847508795276,
            "mjd": 58490.55758400001
        },
        {
            "mag": 17.844788136630754,
            "err": 0.03210242013748738,
            "mjd": 58494.5053375
        },
        {
            "mag": 17.81416763359995,
            "err": 0.031054191902132912,
            "mjd": 58496.55995575
        },
        {
            "mag": 17.87127475443022,
            "err": 0.02708332652446567,
            "mjd": 58498.50892128572
        },
        {
            "mag": 17.870286934441232,
            "err": 0.03222169438660076,
            "mjd": 58500.51273655557
        },
        {
            "mag": 17.874844028312246,
            "err": 0.08534610982925757,
            "mjd": 58502.4935675
        },
        {
            "mag": 17.881152545952553,
            "err": 0.06513403960893588,
            "mjd": 58506.49681325
        },
        {
            "mag": 17.960280787036687,
            "err": 0.03633839787321113,
            "mjd": 58508.48757125001
        },
        {
            "mag": 18.022294919578712,
            "err": 0.03280392222269852,
            "mjd": 58510.479611999996
        },
        {
            "mag": 18.00801231028736,
            "err": 0.037820005198547196,
            "mjd": 58514.48576933334
        },
        {
            "mag": 18.182682840810884,
            "err": 0.04464510459515273,
            "mjd": 58518.469391499995
        },
        {
            "mag": 18.214176064857238,
            "err": 0.04604615131960799,
            "mjd": 58526.476284749995
        },
        {
            "mag": 18.414785705362807,
            "err": 0.09497649968169852,
            "mjd": 58530.460103499994
        },
        {
            "mag": 17.432777464981868,
            "err": 9999,
            "mjd": 58538.44536666666
        },
        {
            "mag": 18.699299252833054,
            "err": 0.08343574465769821,
            "mjd": 58542.449557
        },
        {
            "mag": 19.041751086613058,
            "err": 0.09247364428667573,
            "mjd": 58546.452149
        },
        {
            "mag": 19.40202057958912,
            "err": 0.1124816350172285,
            "mjd": 58550.429798714285
        },
        {
            "mag": 19.427412263526044,
            "err": 0.1344037421275065,
            "mjd": 58554.412897250004
        },
        {
            "mag": 19.266039077326468,
            "err": 9999,
            "mjd": 58558.406816250004
        },
        {
            "mag": 19.2413869140577,
            "err": 0.236318984134888,
            "mjd": 58562.37194775
        },
        {
            "mag": 17.616892048650918,
            "err": 9999,
            "mjd": 58566.40340225
        },
        {
            "mag": 19.625966468646745,
            "err": 0.1189344834866662,
            "mjd": 58568.391311
        },
        {
            "mag": 19.68931867332985,
            "err": 0.1974158019809925,
            "mjd": 58572.36224325
        },
        {
            "mag": 19.766104425556435,
            "err": 0.13987985307002443,
            "mjd": 58578.377648875
        },
        {
            "mag": 19.718766271365762,
            "err": 0.19259824371466933,
            "mjd": 58582.35688025
        },
        {
            "mag": 17.995680409956016,
            "err": 9999,
            "mjd": 58588.373218
        },
        {
            "mag": 18.760729302323686,
            "err": 9999,
            "mjd": 58590.35651600001
        },
        {
            "mag": 19.69241281618428,
            "err": 0.2589855621608932,
            "mjd": 58594.330576
        },
        {
            "mag": 19.921161228656352,
            "err": 0.24502246092241153,
            "mjd": 58596.340075
        },
        {
            "mag": 19.933993912351305,
            "err": 0.2721220148721006,
            "mjd": 58598.32516675
        },
        {
            "mag": 19.341101769811456,
            "err": 9999,
            "mjd": 58600.33076457142
        },
        {
            "mag": 19.71576805662996,
            "err": 0.1638398518194738,
            "mjd": 58610.31429537501
        },
        {
            "mag": 19.58331568311403,
            "err": 9999,
            "mjd": 58614.25272025
        },
        {
            "mag": 19.764887429552715,
            "err": 9999,
            "mjd": 58616.26571825
        },
        {
            "mag": 19.245969790068152,
            "err": 9999,
            "mjd": 58618.258149500005
        },
        {
            "mag": 19.81658094677774,
            "err": 0.22733364512977738,
            "mjd": 58628.24942375
        },
        {
            "mag": 20.173817255000223,
            "err": 9999,
            "mjd": 58758.59045675
        },
        {
            "mag": 18.077009221467947,
            "err": 9999,
            "mjd": 58768.588571
        },
        {
            "mag": 19.928828689053823,
            "err": 9999,
            "mjd": 58770.6214625
        },
        {
            "mag": 20.225617229252748,
            "err": 9999,
            "mjd": 58774.60660975
        },
        {
            "mag": 20.053675897728922,
            "err": 9999,
            "mjd": 58778.61451
        },
        {
            "mag": 20.278383136838677,
            "err": 9999,
            "mjd": 58780.603255625
        },
        {
            "mag": 17.899695707889713,
            "err": 9999,
            "mjd": 58782.636480999994
        },
        {
            "mag": 20.162249257765165,
            "err": 9999,
            "mjd": 58790.55225075
        },
        {
            "mag": 20.210817214752275,
            "err": 9999,
            "mjd": 58794.62827375
        },
        {
            "mag": 19.58930060920177,
            "err": 9999,
            "mjd": 58798.597077750004
        },
        {
            "mag": 19.281286317929585,
            "err": 9999,
            "mjd": 58800.5501695
        },
        {
            "mag": 19.704761717983125,
            "err": 9999,
            "mjd": 58802.58413225
        },
        {
            "mag": 19.609568909920068,
            "err": 9999,
            "mjd": 58804.59399528571
        },
        {
            "mag": 19.040163228621246,
            "err": 9999,
            "mjd": 58814.5462005
        },
        {
            "mag": 18.34722715552109,
            "err": 9999,
            "mjd": 58818.5906765
        },
        {
            "mag": 20.291500699520423,
            "err": 9999,
            "mjd": 58820.6071545
        },
        {
            "mag": 20.266310565951734,
            "err": 9999,
            "mjd": 58822.526669499995
        },
        {
            "mag": 20.268980299407993,
            "err": 9999,
            "mjd": 58824.60722275
        },
        {
            "mag": 20.3927733052512,
            "err": 9999,
            "mjd": 58826.607988250005
        },
        {
            "mag": 19.49597028569901,
            "err": 9999,
            "mjd": 58828.5707135
        },
        {
            "mag": 19.188058146573432,
            "err": 9999,
            "mjd": 58830.5025575
        },
        {
            "mag": 17.316389666924216,
            "err": 9999,
            "mjd": 58832.561115
        },
        {
            "mag": 20.12129205940467,
            "err": 9999,
            "mjd": 58836.49944325
        },
        {
            "mag": 19.75920516182568,
            "err": 9999,
            "mjd": 58838.478244750004
        },
        {
            "mag": 20.596226751241414,
            "err": 9999,
            "mjd": 58846.500287999996
        },
        {
            "mag": 20.16089268021838,
            "err": 9999,
            "mjd": 58850.534778500005
        },
        {
            "mag": 20.106282954845387,
            "err": 9999,
            "mjd": 58866.500887
        },
        {
            "mag": 20.30844928775778,
            "err": 9999,
            "mjd": 58870.43647925
        },
        {
            "mag": 20.550738622876285,
            "err": 9999,
            "mjd": 58874.488375500005
        },
        {
            "mag": 20.458434424726715,
            "err": 9999,
            "mjd": 58878.437146375
        },
        {
            "mag": 20.288368893642236,
            "err": 9999,
            "mjd": 58882.48132466667
        },
        {
            "mag": 19.75074122022571,
            "err": 9999,
            "mjd": 58884.544328749995
        },
        {
            "mag": 20.256484998146313,
            "err": 9999,
            "mjd": 58894.39958975
        },
        {
            "mag": 20.42938106203614,
            "err": 9999,
            "mjd": 58902.37052025
        },
        {
            "mag": 20.176033689850573,
            "err": 9999,
            "mjd": 58910.371692
        },
        {
            "mag": 19.64073088245425,
            "err": 9999,
            "mjd": 58914.4656445
        },
        {
            "mag": 18.05169782429368,
            "err": 9999,
            "mjd": 58916.5483255
        },
        {
            "mag": 19.445295057910673,
            "err": 9999,
            "mjd": 58918.40396975
        },
        {
            "mag": 19.826152778414837,
            "err": 9999,
            "mjd": 58920.369739
        },
        {
            "mag": 14.624731825060955,
            "err": 9999,
            "mjd": 58922.53031125
        },
        {
            "mag": 19.367626349909166,
            "err": 9999,
            "mjd": 58934.323729
        },
        {
            "mag": 19.313640240879717,
            "err": 9999,
            "mjd": 58946.35411674999
        },
        {
            "mag": 19.856670100521754,
            "err": 9999,
            "mjd": 58950.336316249995
        },
        {
            "mag": 20.25548088232015,
            "err": 9999,
            "mjd": 58958.30413375
        },
        {
            "mag": 19.815133056593837,
            "err": 9999,
            "mjd": 58962.3645705
        },
        {
            "mag": 19.968555737733688,
            "err": 9999,
            "mjd": 58966.262743
        },
        {
            "mag": 19.988144636110153,
            "err": 9999,
            "mjd": 58968.27246675
        },
        {
            "mag": 20.181785736193017,
            "err": 9999,
            "mjd": 58970.265128375
        },
        {
            "mag": 19.424502706805253,
            "err": 9999,
            "mjd": 58972.31262525001
        },
        {
            "mag": 19.86991280982091,
            "err": 9999,
            "mjd": 58974.251326
        },
        {
            "mag": 19.191414609233448,
            "err": 9999,
            "mjd": 58976.25178475
        },
        {
            "mag": 19.7561546302665,
            "err": 9999,
            "mjd": 58982.245890750004
        },
        {
            "mag": 20.097248803000024,
            "err": 9999,
            "mjd": 58986.2618745
        },
        {
            "mag": 19.497838097675423,
            "err": 9999,
            "mjd": 59002.2534815
        },
        {
            "mag": 19.497722650224436,
            "err": 9999,
            "mjd": 59126.601574249995
        },
        {
            "mag": 19.91041256460425,
            "err": 9999,
            "mjd": 59130.62686375
        },
        {
            "mag": 19.85516536950761,
            "err": 9999,
            "mjd": 59132.627970500005
        },
        {
            "mag": 18.868735438257286,
            "err": 9999,
            "mjd": 59134.631824000004
        },
        {
            "mag": 19.61042206689401,
            "err": 9999,
            "mjd": 59142.56543425
        },
        {
            "mag": 20.312668928838814,
            "err": 9999,
            "mjd": 59146.6288965
        },
        {
            "mag": 19.68543897833707,
            "err": 9999,
            "mjd": 59154.62674874999
        },
        {
            "mag": 19.50391000898636,
            "err": 9999,
            "mjd": 59156.588797
        },
        {
            "mag": 20.19475780946846,
            "err": 9999,
            "mjd": 59162.59752525
        },
        {
            "mag": 18.848823075860686,
            "err": 9999,
            "mjd": 59170.59388266667
        },
        {
            "mag": 20.455525320760813,
            "err": 9999,
            "mjd": 59178.6049825
        },
        {
            "mag": 19.472115948441576,
            "err": 9999,
            "mjd": 59180.49384475
        },
        {
            "mag": 19.59086608109275,
            "err": 9999,
            "mjd": 59182.48901075
        },
        {
            "mag": 19.65941000594849,
            "err": 9999,
            "mjd": 59184.474147
        },
        {
            "mag": 19.68235945789403,
            "err": 9999,
            "mjd": 59186.553906
        },
        {
            "mag": 20.085416519035725,
            "err": 9999,
            "mjd": 59190.507094
        },
        {
            "mag": 20.192028540517942,
            "err": 9999,
            "mjd": 59192.51737216666
        },
        {
            "mag": 20.146463932667654,
            "err": 9999,
            "mjd": 59208.494875874996
        },
        {
            "mag": 19.401293008400337,
            "err": 9999,
            "mjd": 59212.478297
        },
        {
            "mag": 19.346346306892897,
            "err": 9999,
            "mjd": 59214.434244000004
        },
        {
            "mag": 19.398904199041397,
            "err": 9999,
            "mjd": 59216.445946249994
        },
        {
            "mag": 19.868960238459792,
            "err": 9999,
            "mjd": 59218.52502049999
        },
        {
            "mag": 20.086483297061793,
            "err": 9999,
            "mjd": 59220.532003500004
        },
        {
            "mag": 19.450043777444087,
            "err": 9999,
            "mjd": 59238.3812675
        },
        {
            "mag": 19.358987422258792,
            "err": 9999,
            "mjd": 59244.48789125
        },
        {
            "mag": 19.889214828762434,
            "err": 9999,
            "mjd": 59246.40420166667
        },
        {
            "mag": 19.333893374887207,
            "err": 9999,
            "mjd": 59266.43160425
        },
        {
            "mag": 19.488099807324748,
            "err": 9999,
            "mjd": 59270.4101505
        },
        {
            "mag": 19.53594211194289,
            "err": 9999,
            "mjd": 59278.43966325001
        },
        {
            "mag": 20.252657033368006,
            "err": 9999,
            "mjd": 59292.353310750004
        },
        {
            "mag": 18.81277576337341,
            "err": 9999,
            "mjd": 59298.367907
        },
        {
            "mag": 19.24140137475022,
            "err": 9999,
            "mjd": 59300.363153
        },
        {
            "mag": 19.65433739815243,
            "err": 9999,
            "mjd": 59304.3104725
        },
        {
            "mag": 19.96361232203006,
            "err": 9999,
            "mjd": 59306.427166
        },
        {
            "mag": 19.214262385739257,
            "err": 9999,
            "mjd": 59308.475225250004
        },
        {
            "mag": 20.1658476788086,
            "err": 9999,
            "mjd": 59320.28946074999
        },
        {
            "mag": 20.37412874586796,
            "err": 9999,
            "mjd": 59322.27416749999
        },
        {
            "mag": 19.113180583056483,
            "err": 9999,
            "mjd": 59324.34038375
        },
        {
            "mag": 19.33148598517083,
            "err": 9999,
            "mjd": 59328.271382000006
        },
        {
            "mag": 17.71815513225992,
            "err": 9999,
            "mjd": 59330.30854325001
        },
        {
            "mag": 19.532636660559827,
            "err": 9999,
            "mjd": 59332.28714825
        },
        {
            "mag": 20.310315594943265,
            "err": 9999,
            "mjd": 59334.27697775001
        },
        {
            "mag": 20.109350104389115,
            "err": 9999,
            "mjd": 59342.25333133334
        },
        {
            "mag": 20.29588057868951,
            "err": 9999,
            "mjd": 59346.25410425
        },
        {
            "mag": 19.12970833865629,
            "err": 9999,
            "mjd": 59478.625186749996
        },
        {
            "mag": 19.677321744354817,
            "err": 9999,
            "mjd": 59498.621911
        },
        {
            "mag": 20.1237934761894,
            "err": 9999,
            "mjd": 59500.620183249994
        },
        {
            "mag": 19.634582797129866,
            "err": 9999,
            "mjd": 59502.606951
        },
        {
            "mag": 19.879071829191037,
            "err": 9999,
            "mjd": 59504.61875525
        },
        {
            "mag": 19.31137957727831,
            "err": 9999,
            "mjd": 59510.567816250004
        },
        {
            "mag": 19.448818832125063,
            "err": 9999,
            "mjd": 59514.63291325
        },
        {
            "mag": 18.417374817822353,
            "err": 9999,
            "mjd": 59516.632331333334
        },
        {
            "mag": 19.93784896660539,
            "err": 9999,
            "mjd": 59518.5967135
        },
        {
            "mag": 19.85516536950761,
            "err": 9999,
            "mjd": 59522.6171245
        },
        {
            "mag": 19.819368812829232,
            "err": 9999,
            "mjd": 59526.5482485
        },
        {
            "mag": 19.86559172826831,
            "err": 9999,
            "mjd": 59530.58988475
        },
        {
            "mag": 18.214711518039707,
            "err": 9999,
            "mjd": 59534.414003750004
        },
        {
            "mag": 19.234573972605475,
            "err": 9999,
            "mjd": 59536.508934000005
        },
        {
            "mag": 19.04564510157646,
            "err": 9999,
            "mjd": 59538.570622
        },
        {
            "mag": 19.45764802293607,
            "err": 9999,
            "mjd": 59540.595385500004
        },
        {
            "mag": 19.300614210516706,
            "err": 9999,
            "mjd": 59542.51918050001
        },
        {
            "mag": 19.88125566791033,
            "err": 9999,
            "mjd": 59544.52196575
        },
        {
            "mag": 19.704210440548557,
            "err": 9999,
            "mjd": 59546.48470675
        },
        {
            "mag": 20.022049446084733,
            "err": 9999,
            "mjd": 59550.50139125
        },
        {
            "mag": 19.715563737721894,
            "err": 9999,
            "mjd": 59558.54553125
        },
        {
            "mag": 19.730643927191203,
            "err": 9999,
            "mjd": 59562.530825
        },
        {
            "mag": 19.681047531104447,
            "err": 9999,
            "mjd": 59564.5266595
        },
        {
            "mag": 18.326235281171385,
            "err": 9999,
            "mjd": 59566.4423655
        },
        {
            "mag": 20.078503233347714,
            "err": 9999,
            "mjd": 59574.501321875
        },
        {
            "mag": 19.846246463208736,
            "err": 9999,
            "mjd": 59590.4400765
        },
        {
            "mag": 19.449679633387948,
            "err": 9999,
            "mjd": 59592.44900533333
        },
        {
            "mag": 19.1617860460738,
            "err": 9999,
            "mjd": 59594.435123
        },
        {
            "mag": 18.975935787208094,
            "err": 9999,
            "mjd": 59598.421708999995
        },
        {
            "mag": 19.74054994599621,
            "err": 9999,
            "mjd": 59602.480170500006
        },
        {
            "mag": 20.362682608039233,
            "err": 9999,
            "mjd": 59604.480179499995
        },
        {
            "mag": 20.61116733011371,
            "err": 9999,
            "mjd": 59605.484688125
        },
        {
            "mag": 20.32510566824842,
            "err": 9999,
            "mjd": 59608.408185625
        },
        {
            "mag": 20.007051235703084,
            "err": 9999,
            "mjd": 59609.46722
        },
        {
            "mag": 20.136494116141076,
            "err": 9999,
            "mjd": 59613.39812700001
        },
        {
            "mag": 19.788668943193542,
            "err": 9999,
            "mjd": 59617.453861
        },
        {
            "mag": 20.04400398575403,
            "err": 9999,
            "mjd": 59619.453905999995
        },
        {
            "mag": 19.56613499516807,
            "err": 9999,
            "mjd": 59621.3657975
        },
        {
            "mag": 19.516243312482267,
            "err": 9999,
            "mjd": 59623.344996499996
        },
        {
            "mag": 18.823683133115615,
            "err": 9999,
            "mjd": 59625.47867925
        },
        {
            "mag": 18.747432567171348,
            "err": 9999,
            "mjd": 59626.47239966667
        },
        {
            "mag": 18.954319539179423,
            "err": 9999,
            "mjd": 59627.46131975
        },
        {
            "mag": 19.42172427217087,
            "err": 9999,
            "mjd": 59629.40207175
        },
        {
            "mag": 19.77668020788695,
            "err": 9999,
            "mjd": 59631.41919225
        },
        {
            "mag": 19.97963692196829,
            "err": 9999,
            "mjd": 59633.4169395
        },
        {
            "mag": 19.996186914606007,
            "err": 9999,
            "mjd": 59637.39755275
        },
        {
            "mag": 20.125136187292163,
            "err": 9999,
            "mjd": 59641.427928749996
        },
        {
            "mag": 19.791308509656062,
            "err": 9999,
            "mjd": 59645.38763225
        },
        {
            "mag": 19.69418421468228,
            "err": 9999,
            "mjd": 59647.380674500004
        },
        {
            "mag": 19.648220552604304,
            "err": 9999,
            "mjd": 59649.390624249994
        },
        {
            "mag": 19.079212721499978,
            "err": 9999,
            "mjd": 59655.33162425
        },
        {
            "mag": 19.253044939313607,
            "err": 9999,
            "mjd": 59657.37644
        },
        {
            "mag": 19.788668943193542,
            "err": 9999,
            "mjd": 59659.36475925
        },
        {
            "mag": 19.76701199094947,
            "err": 9999,
            "mjd": 59665.35293
        },
        {
            "mag": 19.416155481729664,
            "err": 9999,
            "mjd": 59673.46811975
        },
        {
            "mag": 19.811687641723918,
            "err": 9999,
            "mjd": 59677.30664025
        },
        {
            "mag": 19.30835875516763,
            "err": 9999,
            "mjd": 59681.34155275
        },
        {
            "mag": 19.523170413169023,
            "err": 9999,
            "mjd": 59683.3465355
        },
        {
            "mag": 18.20457058649294,
            "err": 9999,
            "mjd": 59685.27904075
        },
        {
            "mag": 19.667595719569732,
            "err": 9999,
            "mjd": 59687.27398225
        },
        {
            "mag": 19.769532193359996,
            "err": 9999,
            "mjd": 59689.34282375
        },
        {
            "mag": 19.91087505249506,
            "err": 9999,
            "mjd": 59693.27066275001
        },
        {
            "mag": 19.788493683820796,
            "err": 9999,
            "mjd": 59697.3422255
        },
        {
            "mag": 19.412906420626882,
            "err": 9999,
            "mjd": 59709.252314749996
        },
        {
            "mag": 18.80856806245655,
            "err": 9999,
            "mjd": 59711.256723
        },
        {
            "mag": 18.84794033389226,
            "err": 9999,
            "mjd": 59713.296894
        },
        {
            "mag": 19.03248760903515,
            "err": 9999,
            "mjd": 59715.300583749995
        },
        {
            "mag": 19.47982525386983,
            "err": 9999,
            "mjd": 59721.252823500006
        },
        {
            "mag": 19.190278588530106,
            "err": 9999,
            "mjd": 59729.2949975
        },
        {
            "mag": 19.138653465041724,
            "err": 9999,
            "mjd": 59829.624721
        },
        {
            "mag": 19.418164511798384,
            "err": 9999,
            "mjd": 59837.6165
        },
        {
            "mag": 19.513482407543894,
            "err": 9999,
            "mjd": 59847.590455749996
        },
        {
            "mag": 19.01047777203574,
            "err": 9999,
            "mjd": 59863.62378533333
        },
        {
            "mag": 19.592721769358526,
            "err": 9999,
            "mjd": 59867.615686
        },
        {
            "mag": 19.978669332882234,
            "err": 9999,
            "mjd": 59869.58745775
        },
        {
            "mag": 19.83466625629552,
            "err": 9999,
            "mjd": 59871.62944125
        },
        {
            "mag": 19.607538348366326,
            "err": 9999,
            "mjd": 59873.615871
        },
        {
            "mag": 20.102302479972792,
            "err": 9999,
            "mjd": 59877.575555999996
        },
        {
            "mag": 19.94459726435148,
            "err": 9999,
            "mjd": 59881.6046865
        },
        {
            "mag": 19.87246289050334,
            "err": 9999,
            "mjd": 59885.525987249996
        },
        {
            "mag": 19.40242696321882,
            "err": 9999,
            "mjd": 59893.530677999996
        },
        {
            "mag": 19.54127272333298,
            "err": 9999,
            "mjd": 59895.531365250004
        },
        {
            "mag": 19.991288950959,
            "err": 9999,
            "mjd": 59897.585008999995
        },
        {
            "mag": 20.02753456135073,
            "err": 9999,
            "mjd": 59899.582736
        },
        {
            "mag": 20.188037676727873,
            "err": 9999,
            "mjd": 59901.514891800005
        },
        {
            "mag": 20.23585674675138,
            "err": 9999,
            "mjd": 59907.566435249995
        },
        {
            "mag": 20.01738102169854,
            "err": 9999,
            "mjd": 59915.55538225
        },
        {
            "mag": 18.358541150716924,
            "err": 9999,
            "mjd": 59919.515745
        },
        {
            "mag": 19.86559172826831,
            "err": 9999,
            "mjd": 59959.434699749996
        },
        {
            "mag": 19.992733914518986,
            "err": 9999,
            "mjd": 59963.502499
        },
        {
            "mag": 20.14737966912882,
            "err": 9999,
            "mjd": 59967.492819
        },
        {
            "mag": 19.86720002622505,
            "err": 9999,
            "mjd": 60015.36581449999
        },
        {
            "mag": 20.01148407297157,
            "err": 9999,
            "mjd": 60019.406593
        },
        {
            "mag": 16.932078909199205,
            "err": 9999,
            "mjd": 60023.3371335
        },
        {
            "mag": 17.335914061191954,
            "err": 9999,
            "mjd": 60027.3979785
        },
        {
            "mag": 19.729038547749905,
            "err": 9999,
            "mjd": 60031.323510250004
        },
        {
            "mag": 14.232863336683861,
            "err": 9999,
            "mjd": 60036.349560999995
        },
        {
            "mag": 15.873939990011632,
            "err": 9999,
            "mjd": 60042.36863866667
        },
        {
            "mag": 19.80423586359933,
            "err": 9999,
            "mjd": 60044.358064249995
        },
        {
            "mag": 19.755430751755608,
            "err": 9999,
            "mjd": 60066.260547375
        },
        {
            "mag": 19.4689121541099,
            "err": 9999,
            "mjd": 60068.287317999995
        },
        {
            "mag": 18.116265649535915,
            "err": 9999,
            "mjd": 60070.354521333335
        },
        {
            "mag": 17.97407164340556,
            "err": 9999,
            "mjd": 60072.28540483333
        },
        {
            "mag": 20.06231384690613,
            "err": 9999,
            "mjd": 60082.283416
        },
        {
            "mag": 19.431749253674568,
            "err": 9999,
            "mjd": 60090.256210333326
        },
        {
            "mag": 19.331978481357854,
            "err": 9999,
            "mjd": 60092.265715500005
        }
    ]
}