{
    "c": [
        {
            "mag": 19.824672874565216,
            "err": 0.09701207316720785,
            "mjd": 59219.295322750004
        },
        {
            "mag": 19.089301784845293,
            "err": 0.0581625,
            "mjd": 59221.279585
        },
        {
            "mag": 19.115811202729645,
            "err": 0.1566696308888092,
            "mjd": 59223.296586000004
        },
        {
            "mag": 18.73717801469864,
            "err": 0.039510683366348484,
            "mjd": 59227.3058095
        },
        {
            "mag": 18.932938209020723,
            "err": 0.0656077392703109,
            "mjd": 59229.278472499995
        },
        {
            "mag": 18.798050643628013,
            "err": 0.05100333849550859,
            "mjd": 59231.29610575
        },
        {
            "mag": 20.005522641027238,
            "err": 0.16579617767012442,
            "mjd": 59251.28235975
        },
        {
            "mag": 19.350165818427858,
            "err": 9999,
            "mjd": 59253.28655866667
        },
        {
            "mag": 20.252389872020395,
            "err": 0.17395856170106636,
            "mjd": 59255.241278500005
        },
        {
            "mag": 20.084719133117964,
            "err": 0.17229442214171925,
            "mjd": 59257.24019425
        },
        {
            "mag": 19.21234684152075,
            "err": 9999,
            "mjd": 59259.233613
        },
        {
            "mag": 20.474329368215592,
            "err": 0.3162527822947244,
            "mjd": 59261.23283075
        },
        {
            "mag": 20.41336812187693,
            "err": 9999,
            "mjd": 59431.583327500004
        },
        {
            "mag": 20.768982517412702,
            "err": 9999,
            "mjd": 59435.58734566666
        },
        {
            "mag": 20.56323715026152,
            "err": 9999,
            "mjd": 59439.58487242857
        },
        {
            "mag": 20.526057728911727,
            "err": 9999,
            "mjd": 59443.61302224999
        },
        {
            "mag": 20.554447056882726,
            "err": 9999,
            "mjd": 59461.57151325
        },
        {
            "mag": 20.436086365615104,
            "err": 9999,
            "mjd": 59465.54550325
        },
        {
            "mag": 20.286607802820246,
            "err": 9999,
            "mjd": 59525.48403774999
        },
        {
            "mag": 20.355871112950755,
            "err": 9999,
            "mjd": 59585.30818075
        },
        {
            "mag": 20.52186810442466,
            "err": 9999,
            "mjd": 59603.852672
        },
        {
            "mag": 20.51749361357912,
            "err": 9999,
            "mjd": 59606.83561928571
        },
        {
            "mag": 20.286607802820246,
            "err": 9999,
            "mjd": 59614.824867999996
        },
        {
            "mag": 20.454279962480083,
            "err": 9999,
            "mjd": 59633.047740875
        },
        {
            "mag": 19.946883005025484,
            "err": 9999,
            "mjd": 59789.38891550001
        },
        {
            "mag": 20.724740470578702,
            "err": 9999,
            "mjd": 59792.1224025
        },
        {
            "mag": 20.797946849482827,
            "err": 9999,
            "mjd": 59793.38802714286
        },
        {
            "mag": 20.792404878284263,
            "err": 9999,
            "mjd": 59796.14103225
        },
        {
            "mag": 20.616395531183755,
            "err": 9999,
            "mjd": 59813.29620799999
        },
        {
            "mag": 20.732015158349768,
            "err": 9999,
            "mjd": 59814.3653165
        },
        {
            "mag": 19.76696871556164,
            "err": 9999,
            "mjd": 59818.301211
        },
        {
            "mag": 19.244422476375874,
            "err": 9999,
            "mjd": 59850.981235499996
        },
        {
            "mag": 20.687457990766568,
            "err": 9999,
            "mjd": 59869.146715250004
        },
        {
            "mag": 20.554447056882726,
            "err": 9999,
            "mjd": 59870.234444
        },
        {
            "mag": 20.787777535950188,
            "err": 9999,
            "mjd": 59873.230150749994
        },
        {
            "mag": 20.559576684648114,
            "err": 9999,
            "mjd": 59874.15342266666
        },
        {
            "mag": 20.616395531183755,
            "err": 9999,
            "mjd": 59877.174176333334
        },
        {
            "mag": 20.563987210960164,
            "err": 9999,
            "mjd": 59878.21517325
        },
        {
            "mag": 20.587241245455477,
            "err": 9999,
            "mjd": 59881.216034000005
        },
        {
            "mag": 20.554447056882726,
            "err": 9999,
            "mjd": 59898.84685225
        },
        {
            "mag": 20.618166717428263,
            "err": 9999,
            "mjd": 59899.924460999995
        },
        {
            "mag": 20.658693925869713,
            "err": 9999,
            "mjd": 59902.92690300001
        },
        {
            "mag": 20.792404878284263,
            "err": 9999,
            "mjd": 59903.86800125
        },
        {
            "mag": 20.724740470578702,
            "err": 9999,
            "mjd": 59906.90870775
        },
        {
            "mag": 20.680622857595274,
            "err": 9999,
            "mjd": 59907.91112475
        },
        {
            "mag": 20.724740470578702,
            "err": 9999,
            "mjd": 59910.8970365
        },
        {
            "mag": 20.483790231819043,
            "err": 9999,
            "mjd": 59929.13555125
        },
        {
            "mag": 20.493124935156164,
            "err": 9999,
            "mjd": 59930.12684025
        },
        {
            "mag": 20.529711487501057,
            "err": 9999,
            "mjd": 59934.1362125
        },
        {
            "mag": 20.421854930267383,
            "err": 9999,
            "mjd": 59938.075914333334
        },
        {
            "mag": 20.546117114288535,
            "err": 9999,
            "mjd": 59958.8632535
        },
        {
            "mag": 20.426908663491567,
            "err": 9999,
            "mjd": 59959.80181825
        },
        {
            "mag": 19.36771660839286,
            "err": 9999,
            "mjd": 59962.801882
        },
        {
            "mag": 20.563987210960164,
            "err": 9999,
            "mjd": 59963.84748875
        },
        {
            "mag": 20.31653541695344,
            "err": 9999,
            "mjd": 59967.792220999996
        },
        {
            "mag": 20.178598875506058,
            "err": 9999,
            "mjd": 59991.035706
        },
        {
            "mag": 20.02886248373993,
            "err": 9999,
            "mjd": 60141.116074499994
        },
        {
            "mag": 20.115794296154505,
            "err": 9999,
            "mjd": 60147.12093366667
        }
    ],
    "o": [
        {
            "mag": 19.738364659644702,
            "err": 9999,
            "mjd": 59211.328045
        },
        {
            "mag": 19.368038514286425,
            "err": 9999,
            "mjd": 59213.34473175
        },
        {
            "mag": 18.396695153163563,
            "err": 9999,
            "mjd": 59215.30891925
        },
        {
            "mag": 20.639993095859513,
            "err": 0.2946845431380635,
            "mjd": 59217.295068
        },
        {
            "mag": 19.044654912562713,
            "err": 0.1843562041546095,
            "mjd": 59243.275358
        },
        {
            "mag": 19.101071557170258,
            "err": 0.07914295109477526,
            "mjd": 59245.252430249995
        },
        {
            "mag": 15.743616426521232,
            "err": 9999,
            "mjd": 59265.22964875
        },
        {
            "mag": 20.00986778775133,
            "err": 0.24186849008518932,
            "mjd": 59267.23512125001
        },
        {
            "mag": 19.662237591038078,
            "err": 9999,
            "mjd": 59275.227652500005
        },
        {
            "mag": 20.07738336218595,
            "err": 9999,
            "mjd": 59415.60847425
        },
        {
            "mag": 19.545545890976815,
            "err": 9999,
            "mjd": 59417.586173250005
        },
        {
            "mag": 19.192319700795174,
            "err": 9999,
            "mjd": 59421.612365999994
        },
        {
            "mag": 19.74042781481795,
            "err": 9999,
            "mjd": 59423.613899
        },
        {
            "mag": 19.513805678684683,
            "err": 9999,
            "mjd": 59425.61536775
        },
        {
            "mag": 20.121409320354886,
            "err": 9999,
            "mjd": 59427.613714
        },
        {
            "mag": 20.24545549667614,
            "err": 9999,
            "mjd": 59429.606452
        },
        {
            "mag": 20.21721838593047,
            "err": 9999,
            "mjd": 59433.60976675
        },
        {
            "mag": 20.263850586684164,
            "err": 9999,
            "mjd": 59441.57144825
        },
        {
            "mag": 20.222565593851357,
            "err": 9999,
            "mjd": 59445.552051499995
        },
        {
            "mag": 19.584132983326253,
            "err": 9999,
            "mjd": 59447.511125749996
        },
        {
            "mag": 19.728464935712196,
            "err": 9999,
            "mjd": 59451.56866225
        },
        {
            "mag": 19.578472582453898,
            "err": 9999,
            "mjd": 59453.62900225
        },
        {
            "mag": 20.335890672273983,
            "err": 9999,
            "mjd": 59455.56337624999
        },
        {
            "mag": 20.166041052355446,
            "err": 9999,
            "mjd": 59457.56402675
        },
        {
            "mag": 20.4858759649046,
            "err": 9999,
            "mjd": 59463.498308625
        },
        {
            "mag": 20.02966969076983,
            "err": 9999,
            "mjd": 59467.53045500001
        },
        {
            "mag": 20.002134576457763,
            "err": 9999,
            "mjd": 59471.520706
        },
        {
            "mag": 16.95961477465316,
            "err": 9999,
            "mjd": 59477.45080375
        },
        {
            "mag": 19.04929707856282,
            "err": 9999,
            "mjd": 59479.48752325
        },
        {
            "mag": 19.55197310939356,
            "err": 9999,
            "mjd": 59481.489835500004
        },
        {
            "mag": 19.394562958413967,
            "err": 9999,
            "mjd": 59483.50811124999
        },
        {
            "mag": 20.165481409786835,
            "err": 9999,
            "mjd": 59485.491830499996
        },
        {
            "mag": 19.974935091611673,
            "err": 9999,
            "mjd": 59487.504103
        },
        {
            "mag": 20.125136187292163,
            "err": 9999,
            "mjd": 59489.481178999995
        },
        {
            "mag": 19.996186914606007,
            "err": 9999,
            "mjd": 59491.46744349999
        },
        {
            "mag": 20.148000510428428,
            "err": 9999,
            "mjd": 59493.55202725
        },
        {
            "mag": 19.161912802691734,
            "err": 9999,
            "mjd": 59495.47810875
        },
        {
            "mag": 20.06434477889524,
            "err": 9999,
            "mjd": 59501.46368666666
        },
        {
            "mag": 19.838881099729843,
            "err": 9999,
            "mjd": 59503.42985575
        },
        {
            "mag": 18.77849690950204,
            "err": 9999,
            "mjd": 59505.436537
        },
        {
            "mag": 19.07162075935092,
            "err": 9999,
            "mjd": 59509.496109750005
        },
        {
            "mag": 18.908313569216872,
            "err": 9999,
            "mjd": 59511.48707025
        },
        {
            "mag": 19.902040432791456,
            "err": 9999,
            "mjd": 59513.43236733333
        },
        {
            "mag": 20.033861307089538,
            "err": 9999,
            "mjd": 59515.4126685
        },
        {
            "mag": 20.250761147056895,
            "err": 9999,
            "mjd": 59517.4949655
        },
        {
            "mag": 20.12993792572809,
            "err": 9999,
            "mjd": 59519.40165575
        },
        {
            "mag": 20.04400398575403,
            "err": 9999,
            "mjd": 59523.3940995
        },
        {
            "mag": 19.857308574078637,
            "err": 9999,
            "mjd": 59527.44630375
        },
        {
            "mag": 20.24897655755953,
            "err": 9999,
            "mjd": 59529.380138333334
        },
        {
            "mag": 19.280516285352498,
            "err": 9999,
            "mjd": 59531.365381999996
        },
        {
            "mag": 18.81434011700964,
            "err": 9999,
            "mjd": 59535.42924975
        },
        {
            "mag": 19.87820484898316,
            "err": 9999,
            "mjd": 59537.43451774999
        },
        {
            "mag": 19.41683446172882,
            "err": 9999,
            "mjd": 59539.39561600001
        },
        {
            "mag": 19.919791009073045,
            "err": 9999,
            "mjd": 59541.39287350001
        },
        {
            "mag": 19.769489118415493,
            "err": 9999,
            "mjd": 59543.38873375
        },
        {
            "mag": 19.97963692196829,
            "err": 9999,
            "mjd": 59545.37536375
        },
        {
            "mag": 19.740595379383947,
            "err": 9999,
            "mjd": 59547.40870525
        },
        {
            "mag": 19.988144636110153,
            "err": 9999,
            "mjd": 59551.37754225
        },
        {
            "mag": 19.60248544190908,
            "err": 9999,
            "mjd": 59559.37286825
        },
        {
            "mag": 18.69392169446662,
            "err": 9999,
            "mjd": 59563.3317125
        },
        {
            "mag": 19.149210503760806,
            "err": 9999,
            "mjd": 59569.379935
        },
        {
            "mag": 19.88125566791033,
            "err": 9999,
            "mjd": 59587.30939725
        },
        {
            "mag": 19.73724972823812,
            "err": 9999,
            "mjd": 59589.315982
        },
        {
            "mag": 19.9098145578903,
            "err": 9999,
            "mjd": 59591.554252
        },
        {
            "mag": 19.291428996594078,
            "err": 9999,
            "mjd": 59595.2905865
        },
        {
            "mag": 18.147425010840045,
            "err": 9999,
            "mjd": 59598.876254
        },
        {
            "mag": 20.379126129961623,
            "err": 9999,
            "mjd": 59599.58458550001
        },
        {
            "mag": 19.9519804071656,
            "err": 9999,
            "mjd": 59603.301070999994
        },
        {
            "mag": 19.357854631214483,
            "err": 9999,
            "mjd": 59615.785016999995
        },
        {
            "mag": 19.747037011215568,
            "err": 9999,
            "mjd": 59619.814459249996
        },
        {
            "mag": 19.43786869863475,
            "err": 9999,
            "mjd": 59627.811050250006
        },
        {
            "mag": 20.00672349772074,
            "err": 9999,
            "mjd": 59630.05473824999
        },
        {
            "mag": 20.039537641877565,
            "err": 9999,
            "mjd": 59643.772600000004
        },
        {
            "mag": 12.773992284611584,
            "err": 9999,
            "mjd": 59651.764473
        },
        {
            "mag": 19.491842269944204,
            "err": 9999,
            "mjd": 59654.384524124995
        },
        {
            "mag": 17.6811801994061,
            "err": 9999,
            "mjd": 59656.9956215
        },
        {
            "mag": 18.539718882918706,
            "err": 9999,
            "mjd": 59657.008948999995
        },
        {
            "mag": 18.72492136151113,
            "err": 9999,
            "mjd": 59661.99353
        },
        {
            "mag": 18.9,
            "err": 9999,
            "mjd": 59662.008919
        },
        {
            "mag": 18.40619755158785,
            "err": 9999,
            "mjd": 59664.98956966667
        },
        {
            "mag": 18.389700043360186,
            "err": 9999,
            "mjd": 59665.004118
        },
        {
            "mag": 19.45986240336697,
            "err": 9999,
            "mjd": 59731.173166
        },
        {
            "mag": 19.549319677154102,
            "err": 9999,
            "mjd": 59736.168979333335
        },
        {
            "mag": 20.212887896436467,
            "err": 9999,
            "mjd": 59768.14649025
        },
        {
            "mag": 19.915232871270035,
            "err": 9999,
            "mjd": 59769.41947275
        },
        {
            "mag": 19.668299762764647,
            "err": 9999,
            "mjd": 59776.1078205
        },
        {
            "mag": 20.17286393978886,
            "err": 9999,
            "mjd": 59781.367477
        },
        {
            "mag": 20.264156169637562,
            "err": 9999,
            "mjd": 59782.427181499996
        },
        {
            "mag": 20.021817463076232,
            "err": 9999,
            "mjd": 59785.424200333335
        },
        {
            "mag": 20.25548088232015,
            "err": 9999,
            "mjd": 59786.385824
        },
        {
            "mag": 20.2584610778982,
            "err": 9999,
            "mjd": 59800.059135
        },
        {
            "mag": 18.460812177749155,
            "err": 9999,
            "mjd": 59801.31758133334
        },
        {
            "mag": 18.045718673724835,
            "err": 9999,
            "mjd": 59802.295976500005
        },
        {
            "mag": 19.329686936636293,
            "err": 9999,
            "mjd": 59805.28125933334
        },
        {
            "mag": 19.657669146625683,
            "err": 9999,
            "mjd": 59807.122852
        },
        {
            "mag": 19.915461758438717,
            "err": 9999,
            "mjd": 59808.077689
        },
        {
            "mag": 20.071419893458565,
            "err": 9999,
            "mjd": 59809.334891666665
        },
        {
            "mag": 20.068213438172236,
            "err": 9999,
            "mjd": 59812.086969
        },
        {
            "mag": 20.41336812187693,
            "err": 9999,
            "mjd": 59815.0861115
        },
        {
            "mag": 20.190661531033648,
            "err": 9999,
            "mjd": 59819.042480000004
        },
        {
            "mag": 20.663635620846144,
            "err": 9999,
            "mjd": 59824.027070125
        },
        {
            "mag": 20.611460287102265,
            "err": 9999,
            "mjd": 59828.13201214286
        },
        {
            "mag": 20.050059594963376,
            "err": 9999,
            "mjd": 59831.31347957143
        },
        {
            "mag": 19.80324450800601,
            "err": 9999,
            "mjd": 59834.224167875
        },
        {
            "mag": 19.265889757223086,
            "err": 9999,
            "mjd": 59835.006885999996
        },
        {
            "mag": 19.618328727231066,
            "err": 9999,
            "mjd": 59836.0175375
        },
        {
            "mag": 20.289845329711323,
            "err": 9999,
            "mjd": 59842.92889833334
        },
        {
            "mag": 20.455525320760813,
            "err": 9999,
            "mjd": 59845.231056000004
        },
        {
            "mag": 20.37090371639102,
            "err": 9999,
            "mjd": 59846.27245575
        },
        {
            "mag": 19.68628795689765,
            "err": 9999,
            "mjd": 59849.26389225
        },
        {
            "mag": 16.39821494054089,
            "err": 9999,
            "mjd": 59850.238485
        },
        {
            "mag": 20.618166717428263,
            "err": 9999,
            "mjd": 59853.231822
        },
        {
            "mag": 20.831195656036826,
            "err": 9999,
            "mjd": 59854.5947065
        },
        {
            "mag": 20.117770822770545,
            "err": 9999,
            "mjd": 59855.94398025
        },
        {
            "mag": 19.76934001585615,
            "err": 9999,
            "mjd": 59858.556999875
        },
        {
            "mag": 19.28161779115902,
            "err": 9999,
            "mjd": 59859.9419
        },
        {
            "mag": 18.76521406461886,
            "err": 9999,
            "mjd": 59861.135883
        },
        {
            "mag": 18.879201966717922,
            "err": 9999,
            "mjd": 59862.2978895
        },
        {
            "mag": 19.290540034708933,
            "err": 9999,
            "mjd": 59865.33536599999
        },
        {
            "mag": 20.107552980341367,
            "err": 9999,
            "mjd": 59866.487482428565
        },
        {
            "mag": 20.772047306968517,
            "err": 9999,
            "mjd": 59871.35417158334
        },
        {
            "mag": 20.188947477487982,
            "err": 9999,
            "mjd": 59874.909120000004
        },
        {
            "mag": 20.218519887450967,
            "err": 9999,
            "mjd": 59875.968113250005
        },
        {
            "mag": 20.18222456677048,
            "err": 9999,
            "mjd": 59878.947572666664
        },
        {
            "mag": 20.281504972622756,
            "err": 9999,
            "mjd": 59879.70403860001
        },
        {
            "mag": 20.25435292359156,
            "err": 9999,
            "mjd": 59882.397670666665
        },
        {
            "mag": 20.24488144401448,
            "err": 9999,
            "mjd": 59883.649850333335
        },
        {
            "mag": 19.968412812916,
            "err": 9999,
            "mjd": 59885.137164
        },
        {
            "mag": 19.723176684100512,
            "err": 9999,
            "mjd": 59886.22409066666
        },
        {
            "mag": 18.045542817943247,
            "err": 9999,
            "mjd": 59887.848689499995
        },
        {
            "mag": 19.59502404056167,
            "err": 9999,
            "mjd": 59889.22677025
        },
        {
            "mag": 19.14604218870675,
            "err": 9999,
            "mjd": 59890.871641499994
        },
        {
            "mag": 17.620291597552814,
            "err": 9999,
            "mjd": 59891.952045
        },
        {
            "mag": 20.28680275716947,
            "err": 0.30080671211644733,
            "mjd": 59894.51038085715
        },
        {
            "mag": 20.01923746113757,
            "err": 9999,
            "mjd": 59895.84491175
        },
        {
            "mag": 20.256484998146313,
            "err": 9999,
            "mjd": 59897.18812875
        },
        {
            "mag": 20.125136187292163,
            "err": 9999,
            "mjd": 59898.11989625
        },
        {
            "mag": 20.210817214752275,
            "err": 9999,
            "mjd": 59901.14476350001
        },
        {
            "mag": 20.38106951503683,
            "err": 9999,
            "mjd": 59902.20623150001
        },
        {
            "mag": 20.493124935156164,
            "err": 9999,
            "mjd": 59905.184639
        },
        {
            "mag": 20.169559246522983,
            "err": 9999,
            "mjd": 59906.165456999996
        },
        {
            "mag": 20.35173889028088,
            "err": 9999,
            "mjd": 59909.211700500004
        },
        {
            "mag": 20.503794821451926,
            "err": 9999,
            "mjd": 59910.166719500005
        },
        {
            "mag": 19.99212507369127,
            "err": 9999,
            "mjd": 59911.901710750004
        },
        {
            "mag": 20.07209114036277,
            "err": 9999,
            "mjd": 59913.150638499996
        },
        {
            "mag": 20.27132751309137,
            "err": 9999,
            "mjd": 59914.48296825
        },
        {
            "mag": 19.665813599632756,
            "err": 9999,
            "mjd": 59915.900496
        },
        {
            "mag": 19.479825121152043,
            "err": 9999,
            "mjd": 59917.117149000005
        },
        {
            "mag": 19.344035250953247,
            "err": 9999,
            "mjd": 59918.402658833336
        },
        {
            "mag": 19.53120354012185,
            "err": 9999,
            "mjd": 59919.867238750005
        },
        {
            "mag": 19.359146356000558,
            "err": 9999,
            "mjd": 59921.1475765
        },
        {
            "mag": 20.06670960739423,
            "err": 9999,
            "mjd": 59922.49589025
        },
        {
            "mag": 20.097248803000024,
            "err": 9999,
            "mjd": 59925.10878625
        },
        {
            "mag": 20.41765523006938,
            "err": 9999,
            "mjd": 59926.521608333336
        },
        {
            "mag": 20.25990666636748,
            "err": 9999,
            "mjd": 59927.849023333336
        },
        {
            "mag": 20.587241245455477,
            "err": 9999,
            "mjd": 59931.88653375
        },
        {
            "mag": 20.329445896058974,
            "err": 9999,
            "mjd": 59934.88680625
        },
        {
            "mag": 20.25990666636748,
            "err": 9999,
            "mjd": 59935.84117200001
        },
        {
            "mag": 20.44385251703679,
            "err": 9999,
            "mjd": 59938.8365265
        },
        {
            "mag": 20.38106951503683,
            "err": 9999,
            "mjd": 59939.861485
        },
        {
            "mag": 20.335890672273983,
            "err": 9999,
            "mjd": 59941.081459
        },
        {
            "mag": 20.472811373115917,
            "err": 9999,
            "mjd": 59942.48065775
        },
        {
            "mag": 19.898042307667698,
            "err": 9999,
            "mjd": 59943.8333215
        },
        {
            "mag": 19.662802961335828,
            "err": 9999,
            "mjd": 59945.09159675
        },
        {
            "mag": 20.059223217288295,
            "err": 9999,
            "mjd": 59946.457674875
        },
        {
            "mag": 19.613789397536998,
            "err": 9999,
            "mjd": 59947.83941275
        },
        {
            "mag": 19.896890090951246,
            "err": 9999,
            "mjd": 59950.40026785715
        },
        {
            "mag": 19.82643478209432,
            "err": 9999,
            "mjd": 59951.8137845
        },
        {
            "mag": 19.934883001606615,
            "err": 9999,
            "mjd": 59953.085019
        },
        {
            "mag": 20.44477667064278,
            "err": 9999,
            "mjd": 59954.429489
        },
        {
            "mag": 19.665380148001802,
            "err": 9999,
            "mjd": 59955.863283666666
        },
        {
            "mag": 19.80423586359933,
            "err": 9999,
            "mjd": 59957.0597425
        },
        {
            "mag": 20.2795465752762,
            "err": 9999,
            "mjd": 59958.08315375
        },
        {
            "mag": 19.9503223895418,
            "err": 9999,
            "mjd": 59961.10203933334
        },
        {
            "mag": 19.85520215581887,
            "err": 9999,
            "mjd": 59962.05128874999
        },
        {
            "mag": 19.96962965095428,
            "err": 9999,
            "mjd": 59965.04814175
        },
        {
            "mag": 20.379703518735802,
            "err": 9999,
            "mjd": 59969.074872
        },
        {
            "mag": 20.19165293245466,
            "err": 9999,
            "mjd": 59970.29260425
        },
        {
            "mag": 19.918535447182755,
            "err": 9999,
            "mjd": 59971.82339666667
        },
        {
            "mag": 19.51741280547492,
            "err": 9999,
            "mjd": 59973.041222500004
        },
        {
            "mag": 20.260427657792874,
            "err": 9999,
            "mjd": 59974.315171833325
        },
        {
            "mag": 19.49646177169253,
            "err": 9999,
            "mjd": 59975.78532375
        },
        {
            "mag": 19.49883462791422,
            "err": 9999,
            "mjd": 59977.061230750005
        },
        {
            "mag": 19.032376503621006,
            "err": 9999,
            "mjd": 59978.0382825
        },
        {
            "mag": 19.563813322897047,
            "err": 9999,
            "mjd": 59979.797276000005
        },
        {
            "mag": 19.614572637228786,
            "err": 9999,
            "mjd": 59982.36935914285
        },
        {
            "mag": 20.108843463825664,
            "err": 9999,
            "mjd": 59989.79033025
        },
        {
            "mag": 19.679133072585593,
            "err": 9999,
            "mjd": 59997.77365925
        },
        {
            "mag": 19.656437759511437,
            "err": 9999,
            "mjd": 60005.766148124996
        },
        {
            "mag": 19.287637154787543,
            "err": 9999,
            "mjd": 60007.0246195
        },
        {
            "mag": 18.872613117607806,
            "err": 9999,
            "mjd": 60015.010495250004
        },
        {
            "mag": 16.541220466450838,
            "err": 9999,
            "mjd": 60106.4178468
        },
        {
            "mag": 19.879205124767786,
            "err": 9999,
            "mjd": 60126.13291525
        },
        {
            "mag": 18.80215324118827,
            "err": 9999,
            "mjd": 60127.367037
        },
        {
            "mag": 19.20977359652835,
            "err": 9999,
            "mjd": 60130.3495995
        },
        {
            "mag": 19.299597698477626,
            "err": 9999,
            "mjd": 60132.1467755
        },
        {
            "mag": 19.528727213682693,
            "err": 9999,
            "mjd": 60133.39969325
        },
        {
            "mag": 19.714606038988137,
            "err": 9999,
            "mjd": 60136.391306749996
        },
        {
            "mag": 20.144587056355196,
            "err": 9999,
            "mjd": 60138.1477255
        },
        {
            "mag": 20.222565593851357,
            "err": 9999,
            "mjd": 60139.3745195
        },
        {
            "mag": 20.192648126795813,
            "err": 9999,
            "mjd": 60148.36608575
        },
        {
            "mag": 20.12993792572809,
            "err": 9999,
            "mjd": 60151.365031999994
        }
    ]
}